LICENSE
MANIFEST.in
README
README.rst
setup.py
bin/frontweb
frontweb/__init__.py
frontweb/comandos.py
frontweb/conversor.py
frontweb/html.py
frontweb/models.py
frontweb/pluginsmanager.py
frontweb/sample_settings.py
frontweb/sample_url.py
frontweb/settings.py
frontweb/subcommand.py
frontweb/tests.py
frontweb/urls.py
frontweb/utils.py
frontweb/views.py
frontweb.egg-info/PKG-INFO
frontweb.egg-info/SOURCES.txt
frontweb.egg-info/dependency_links.txt
frontweb.egg-info/requires.txt
frontweb.egg-info/top_level.txt
frontweb/data/2011-01-02-noticia_de_ejemplo.rst
frontweb/data/README
frontweb/data/acercade.rst
frontweb/data/configuracion.ini
frontweb/data/fixture.rst
frontweb/data/footer.rst
frontweb/data/index.rst
frontweb/data/navbar.rst
frontweb/data/primeros_pasos.rst
frontweb/data/sidebar.rst
frontweb/data/sintaxis.rst
frontweb/data/title.rst
frontweb/data/fixtures/fixture.rst
frontweb/data/icons/folder.png
frontweb/data/icons/txt.png
frontweb/data/images/logo-frontweb.png
frontweb/data/images/manzana.png
frontweb/data/theme/custom_dark.css
frontweb/data/theme/css/base.css
frontweb/data/theme/css/custom.css
frontweb/data/theme/css/syntax.css
frontweb/data/theme/images/headers/cactii.jpg
frontweb/directives/__init__.py
frontweb/directives/gallery_directive.py
frontweb/directives/pygments_code_block_directive.py
frontweb/directives/sample_directive.py
frontweb/directives/search_directive.py
frontweb/directives/tags_directive.py
frontweb/directives/toctree_directive.py
frontweb/management/commands/__init__.py
frontweb/management/commands/frontweb_plugin.py
frontweb/plugins/feed.py
frontweb/plugins/feed.yapsy-plugin
frontweb/plugins/find.py
frontweb/plugins/find.yapsy-plugin
frontweb/plugins/ls.py
frontweb/plugins/ls.yapsy-plugin
frontweb/plugins/raw.py
frontweb/plugins/raw.yapsy-plugin
frontweb/plugins/update.py
frontweb/plugins/update.yapsy-plugin
frontweb/templates/frontweb/404.html
frontweb/templates/frontweb/500.html
frontweb/templates/frontweb/message.html
frontweb/templates/frontweb/page.html
frontweb/templates/frontweb/plugins.html
frontweb/templates/frontweb/show.html
frontweb/yapsy/AutoInstallPluginManager.py
