Metadata-Version: 1.0
Name: frontweb
Version: 0.41
Summary: A simple website builder using restructured text
Home-page: http://www.frontweb.com.ar
Author: Hugo Ruscitti
Author-email: hugoruscitti@gmail.com
License: GPLv3
Platform: UNKNOWN
